naver_api/__init__.py
naver_api/naver_search.py
water/__init__.py
water/chosun.py
water/hani.py
water/kofiabond.py
water/krawler.py
water/naver.py
water/naver_search.py
water/utils.py
krawler_api-0.21.5.dist-info/METADATA
krawler_api-0.21.5.dist-info/WHEEL
krawler_api-0.21.5.dist-info/top_level.txt
krawler_api-0.21.5.dist-info/RECORD
