Metadata-Version: 2.1
Name: krawler-api
Version: 0.21.5
Summary: A general container of apis out of Naver, Kakao
Home-page: https://github.com/harry81/krawler
Author: Hyunmin Choi
Author-email: pointer81@gmail.com
License: MIT
Platform: UNKNOWN
Requires-Dist: bs4
Requires-Dist: lxml
Requires-Dist: requests
